{
    "companyName": "Slope",
    "productName": "Slope",
    "dataUrl": "https://cdn.jsdelivr.net/gh/Browncha023/Vengeance@main/other/slope/slope_27Sept.data.unityweb",
    "wasmCodeUrl": "https://cdn.jsdelivr.net/gh/Browncha023/Vengeance@main/other/slope/slope_27Sept.wasm.code.unityweb",
    "wasmFrameworkUrl": "slope_27Sept.wasm.framework.unityweb",
    "asmCodeUrl": "https://cdn.jsdelivr.net/gh/Browncha023/Vengeance@main/other/slope/slope_27Sept.asm.code.unityweb",
    "asmMemoryUrl": "https://cdn.jsdelivr.net/gh/Browncha023/Vengeance@main/other/slope/slope_27Sept.asm.memory.unityweb",
    "asmFrameworkUrl": "https://cdn.jsdelivr.net/gh/Browncha023/Vengeance@main/other/slope/slope_27Sept.asm.framework.unityweb",
    "TOTAL_MEMORY": 268435456,
    "graphicsAPI": ["WebGL 2.0", "WebGL 1.0"],
    "webglContextAttributes": {"preserveDrawingBuffer": false},
    "splashScreenStyle": "Dark",
    "backgroundColor": "#231F20"
    }